[{"id":1706752800,"dateTime":"2024-02-01T02:00:00.000Z","treatmentName":"scrub","userId":1},{"id":1706767200,"dateTime":"2024-02-01T06:00:00.000Z","treatmentName":"scrub","userId":100},{"id":1706853600,"dateTime":"2024-02-02T06:00:00.000Z","treatmentName":"massage"},{"id":1706860800,"dateTime":"2024-02-02T08:00:00.000Z","treatmentName":"massage"},{"id":1707102000,"dateTime":"2024-02-05T03:00:00.000Z","treatmentName":"massage","userId":100},{"id":1707116400,"dateTime":"2024-02-05T07:00:00.000Z","treatmentName":"facial","userId":100},{"id":1707199200,"dateTime":"2024-02-06T06:00:00.000Z","treatmentName":"scrub","userId":1},{"id":1707206400,"dateTime":"2024-02-06T08:00:00.000Z","treatmentName":"massage"},{"id":1707278400,"dateTime":"2024-02-07T04:00:00.000Z","treatmentName":"facial"},{"id":1707296400,"dateTime":"2024-02-07T09:00:00.000Z","treatmentName":"scrub","userId":100},{"id":1707357600,"dateTime":"2024-02-08T02:00:00.000Z","treatmentName":"scrub"},{"id":1707372000,"dateTime":"2024-02-08T06:00:00.000Z","treatmentName":"scrub"},{"id":1707458400,"dateTime":"2024-02-09T06:00:00.000Z","treatmentName":"massage"},{"id":1707465600,"dateTime":"2024-02-09T08:00:00.000Z","treatmentName":"massage","userId":100},{"id":1707706800,"dateTime":"2024-02-12T03:00:00.000Z","treatmentName":"massage","userId":100},{"id":1707721200,"dateTime":"2024-02-12T07:00:00.000Z","treatmentName":"facial"},{"id":1707804000,"dateTime":"2024-02-13T06:00:00.000Z","treatmentName":"scrub"},{"id":1707811200,"dateTime":"2024-02-13T08:00:00.000Z","treatmentName":"massage","userId":100},{"id":1707883200,"dateTime":"2024-02-14T04:00:00.000Z","treatmentName":"facial","userId":100},{"id":1707901200,"dateTime":"2024-02-14T09:00:00.000Z","treatmentName":"scrub"},{"id":1707962400,"dateTime":"2024-02-15T02:00:00.000Z","treatmentName":"scrub","userId":100},{"id":1707976800,"dateTime":"2024-02-15T06:00:00.000Z","treatmentName":"scrub"},{"id":1708063200,"dateTime":"2024-02-16T06:00:00.000Z","treatmentName":"massage","userId":100},{"id":1708070400,"dateTime":"2024-02-16T08:00:00.000Z","treatmentName":"massage","userId":100},{"id":1708311600,"dateTime":"2024-02-19T03:00:00.000Z","treatmentName":"massage","userId":100},{"id":1708326000,"dateTime":"2024-02-19T07:00:00.000Z","treatmentName":"facial"},{"id":1708408800,"dateTime":"2024-02-20T06:00:00.000Z","treatmentName":"scrub","userId":100},{"id":1708416000,"dateTime":"2024-02-20T08:00:00.000Z","treatmentName":"massage","userId":100},{"id":1708488000,"dateTime":"2024-02-21T04:00:00.000Z","treatmentName":"facial"},{"id":1708506000,"dateTime":"2024-02-21T09:00:00.000Z","treatmentName":"scrub","userId":100},{"id":1708567200,"dateTime":"2024-02-22T02:00:00.000Z","treatmentName":"scrub"},{"id":1708581600,"dateTime":"2024-02-22T06:00:00.000Z","treatmentName":"scrub"},{"id":1708668000,"dateTime":"2024-02-23T06:00:00.000Z","treatmentName":"massage","userId":100},{"id":1708675200,"dateTime":"2024-02-23T08:00:00.000Z","treatmentName":"massage"},{"id":1708916400,"dateTime":"2024-02-26T03:00:00.000Z","treatmentName":"massage","userId":100},{"id":1708930800,"dateTime":"2024-02-26T07:00:00.000Z","treatmentName":"facial"},{"id":1709013600,"dateTime":"2024-02-27T06:00:00.000Z","treatmentName":"scrub"},{"id":1709020800,"dateTime":"2024-02-27T08:00:00.000Z","treatmentName":"massage"},{"id":1709092800,"dateTime":"2024-02-28T04:00:00.000Z","treatmentName":"facial","userId":100},{"id":1709110800,"dateTime":"2024-02-28T09:00:00.000Z","treatmentName":"scrub"},{"id":1709172000,"dateTime":"2024-02-29T02:00:00.000Z","treatmentName":"scrub"},{"id":1709186400,"dateTime":"2024-02-29T06:00:00.000Z","treatmentName":"scrub","userId":100},{"id":1709272800,"dateTime":"2024-03-01T06:00:00.000Z","treatmentName":"massage"},{"id":1709280000,"dateTime":"2024-03-01T08:00:00.000Z","treatmentName":"massage","userId":100},{"id":1709521200,"dateTime":"2024-03-04T03:00:00.000Z","treatmentName":"massage"},{"id":1709535600,"dateTime":"2024-03-04T07:00:00.000Z","treatmentName":"facial","userId":1},{"id":1709618400,"dateTime":"2024-03-05T06:00:00.000Z","treatmentName":"scrub"},{"id":1709625600,"dateTime":"2024-03-05T08:00:00.000Z","treatmentName":"massage"},{"id":1709697600,"dateTime":"2024-03-06T04:00:00.000Z","treatmentName":"facial"},{"id":1709715600,"dateTime":"2024-03-06T09:00:00.000Z","treatmentName":"scrub","userId":100},{"id":1709776800,"dateTime":"2024-03-07T02:00:00.000Z","treatmentName":"scrub"},{"id":1709791200,"dateTime":"2024-03-07T06:00:00.000Z","treatmentName":"scrub","userId":100},{"id":1709877600,"dateTime":"2024-03-08T06:00:00.000Z","treatmentName":"massage"},{"id":1709884800,"dateTime":"2024-03-08T08:00:00.000Z","treatmentName":"massage"},{"id":1710126000,"dateTime":"2024-03-11T03:00:00.000Z","treatmentName":"massage"},{"id":1710140400,"dateTime":"2024-03-11T07:00:00.000Z","treatmentName":"facial"},{"id":1710223200,"dateTime":"2024-03-12T06:00:00.000Z","treatmentName":"scrub"},{"id":1710230400,"dateTime":"2024-03-12T08:00:00.000Z","treatmentName":"massage"},{"id":1710302400,"dateTime":"2024-03-13T04:00:00.000Z","treatmentName":"facial"},{"id":1710320400,"dateTime":"2024-03-13T09:00:00.000Z","treatmentName":"scrub"},{"id":1710381600,"dateTime":"2024-03-14T02:00:00.000Z","treatmentName":"scrub"},{"id":1710396000,"dateTime":"2024-03-14T06:00:00.000Z","treatmentName":"scrub","userId":100},{"id":1710482400,"dateTime":"2024-03-15T06:00:00.000Z","treatmentName":"massage"},{"id":1710489600,"dateTime":"2024-03-15T08:00:00.000Z","treatmentName":"massage","userId":100},{"id":1710730800,"dateTime":"2024-03-18T03:00:00.000Z","treatmentName":"massage"},{"id":1710745200,"dateTime":"2024-03-18T07:00:00.000Z","treatmentName":"facial","userId":100},{"id":1710828000,"dateTime":"2024-03-19T06:00:00.000Z","treatmentName":"scrub","userId":100},{"id":1710835200,"dateTime":"2024-03-19T08:00:00.000Z","treatmentName":"massage","userId":100},{"id":1710907200,"dateTime":"2024-03-20T04:00:00.000Z","treatmentName":"facial","userId":100},{"id":1710925200,"dateTime":"2024-03-20T09:00:00.000Z","treatmentName":"scrub","userId":100},{"id":1710986400,"dateTime":"2024-03-21T02:00:00.000Z","treatmentName":"scrub"},{"id":1711000800,"dateTime":"2024-03-21T06:00:00.000Z","treatmentName":"scrub"},{"id":1711087200,"dateTime":"2024-03-22T06:00:00.000Z","treatmentName":"massage"},{"id":1711094400,"dateTime":"2024-03-22T08:00:00.000Z","treatmentName":"massage","userId":100},{"id":1711335600,"dateTime":"2024-03-25T03:00:00.000Z","treatmentName":"massage"},{"id":1711350000,"dateTime":"2024-03-25T07:00:00.000Z","treatmentName":"facial"},{"id":1711432800,"dateTime":"2024-03-26T06:00:00.000Z","treatmentName":"scrub","userId":100},{"id":1711440000,"dateTime":"2024-03-26T08:00:00.000Z","treatmentName":"massage"},{"id":1711512000,"dateTime":"2024-03-27T04:00:00.000Z","treatmentName":"facial"},{"id":1711530000,"dateTime":"2024-03-27T09:00:00.000Z","treatmentName":"scrub"},{"id":1711591200,"dateTime":"2024-03-28T02:00:00.000Z","treatmentName":"scrub"},{"id":1711605600,"dateTime":"2024-03-28T06:00:00.000Z","treatmentName":"scrub"},{"id":1711692000,"dateTime":"2024-03-29T06:00:00.000Z","treatmentName":"massage"},{"id":1711699200,"dateTime":"2024-03-29T08:00:00.000Z","treatmentName":"massage","userId":100},{"id":1711940400,"dateTime":"2024-04-01T03:00:00.000Z","treatmentName":"massage"},{"id":1711954800,"dateTime":"2024-04-01T07:00:00.000Z","treatmentName":"facial","userId":100},{"id":1712037600,"dateTime":"2024-04-02T06:00:00.000Z","treatmentName":"scrub","userId":100},{"id":1712044800,"dateTime":"2024-04-02T08:00:00.000Z","treatmentName":"massage"},{"id":1712116800,"dateTime":"2024-04-03T04:00:00.000Z","treatmentName":"facial"},{"id":1712134800,"dateTime":"2024-04-03T09:00:00.000Z","treatmentName":"scrub"},{"id":1712196000,"dateTime":"2024-04-04T02:00:00.000Z","treatmentName":"scrub","userId":1},{"id":1712210400,"dateTime":"2024-04-04T06:00:00.000Z","treatmentName":"scrub","userId":1},{"id":1712296800,"dateTime":"2024-04-05T06:00:00.000Z","treatmentName":"massage","userId":1},{"id":1712304000,"dateTime":"2024-04-05T08:00:00.000Z","treatmentName":"massage","userId":1},{"id":1712545200,"dateTime":"2024-04-08T03:00:00.000Z","treatmentName":"massage","userId":100},{"id":1712559600,"dateTime":"2024-04-08T07:00:00.000Z","treatmentName":"facial"},{"id":1712642400,"dateTime":"2024-04-09T06:00:00.000Z","treatmentName":"scrub","userId":1},{"id":1712649600,"dateTime":"2024-04-09T08:00:00.000Z","treatmentName":"massage"},{"id":1712721600,"dateTime":"2024-04-10T04:00:00.000Z","treatmentName":"facial"},{"id":1712739600,"dateTime":"2024-04-10T09:00:00.000Z","treatmentName":"scrub"},{"id":1712800800,"dateTime":"2024-04-11T02:00:00.000Z","treatmentName":"scrub","userId":100},{"id":1712815200,"dateTime":"2024-04-11T06:00:00.000Z","treatmentName":"scrub","userId":100},{"id":1712901600,"dateTime":"2024-04-12T06:00:00.000Z","treatmentName":"massage"},{"id":1712908800,"dateTime":"2024-04-12T08:00:00.000Z","treatmentName":"massage","userId":100},{"id":1713150000,"dateTime":"2024-04-15T03:00:00.000Z","treatmentName":"massage"},{"id":1713164400,"dateTime":"2024-04-15T07:00:00.000Z","treatmentName":"facial","userId":100},{"id":1713247200,"dateTime":"2024-04-16T06:00:00.000Z","treatmentName":"scrub","userId":100},{"id":1713254400,"dateTime":"2024-04-16T08:00:00.000Z","treatmentName":"massage"},{"id":1713326400,"dateTime":"2024-04-17T04:00:00.000Z","treatmentName":"facial"},{"id":1713344400,"dateTime":"2024-04-17T09:00:00.000Z","treatmentName":"scrub"},{"id":1713405600,"dateTime":"2024-04-18T02:00:00.000Z","treatmentName":"scrub"},{"id":1713420000,"dateTime":"2024-04-18T06:00:00.000Z","treatmentName":"scrub"},{"id":1713506400,"dateTime":"2024-04-19T06:00:00.000Z","treatmentName":"massage","userId":100},{"id":1713513600,"dateTime":"2024-04-19T08:00:00.000Z","treatmentName":"massage","userId":100},{"id":1713754800,"dateTime":"2024-04-22T03:00:00.000Z","treatmentName":"massage","userId":100},{"id":1713769200,"dateTime":"2024-04-22T07:00:00.000Z","treatmentName":"facial","userId":100},{"id":1713852000,"dateTime":"2024-04-23T06:00:00.000Z","treatmentName":"scrub"},{"id":1713859200,"dateTime":"2024-04-23T08:00:00.000Z","treatmentName":"massage"},{"id":1713931200,"dateTime":"2024-04-24T04:00:00.000Z","treatmentName":"facial"},{"id":1713949200,"dateTime":"2024-04-24T09:00:00.000Z","treatmentName":"scrub"},{"id":1714010400,"dateTime":"2024-04-25T02:00:00.000Z","treatmentName":"scrub"},{"id":1714024800,"dateTime":"2024-04-25T06:00:00.000Z","treatmentName":"scrub","userId":100},{"id":1714111200,"dateTime":"2024-04-26T06:00:00.000Z","treatmentName":"massage"},{"id":1714118400,"dateTime":"2024-04-26T08:00:00.000Z","treatmentName":"massage"},{"id":1714359600,"dateTime":"2024-04-29T03:00:00.000Z","treatmentName":"massage"},{"id":1714374000,"dateTime":"2024-04-29T07:00:00.000Z","treatmentName":"facial"},{"id":1714456800,"dateTime":"2024-04-30T06:00:00.000Z","treatmentName":"scrub"},{"id":1714464000,"dateTime":"2024-04-30T08:00:00.000Z","treatmentName":"massage","userId":100}]